MANIFEST.in
setup.py
alamire_of_tamir/__init__.py
alamire_of_tamir/command_line.py
alamire_of_tamir/midi_writer.py
alamire_of_tamir/process_classes.py
alamire_of_tamir/read_write_init.py
alamire_of_tamir/script_test.py
alamire_of_tamir/script_translation.py
alamire_of_tamir.egg-info/PKG-INFO
alamire_of_tamir.egg-info/SOURCES.txt
alamire_of_tamir.egg-info/dependency_links.txt
alamire_of_tamir.egg-info/entry_points.txt
alamire_of_tamir.egg-info/not-zip-safe
alamire_of_tamir.egg-info/requires.txt
alamire_of_tamir.egg-info/top_level.txt
alamire_of_tamir/data_alamire/demo.annotation
alamire_of_tamir/data_alamire/demo_image.jpg