Metadata-Version: 1.1
Name: alamire-of-tamir
Version: 0.15
Summary: Translate the manuscripts
Home-page: https://github.com/zb8c5ek/alamire_of_tamir
Author: RemovedAuthorInformationDueToDoubleBlindReview
Author-email: RemovedAuthorContactDueToDoubleBlindReview
License: MIT
Keywords: Manuscript Transcription,Alamire,TAMIR
Platform: UNKNOWN
Classifier: License :: OSI Approved :: MIT License
Classifier: Programming Language :: Python :: 2
Classifier: Programming Language :: Python :: 2.6
Classifier: Programming Language :: Python :: 2.7
